hvac/__init__.py
hvac/adapters.py
hvac/api/__init__.py
hvac/api/auth_methods/__init__.py
hvac/api/auth_methods/approle.py
hvac/api/auth_methods/aws.py
hvac/api/auth_methods/azure.py
hvac/api/auth_methods/cert.py
hvac/api/auth_methods/gcp.py
hvac/api/auth_methods/github.py
hvac/api/auth_methods/jwt.py
hvac/api/auth_methods/kubernetes.py
hvac/api/auth_methods/ldap.py
hvac/api/auth_methods/legacy_mfa.py
hvac/api/auth_methods/mfa.py
hvac/api/auth_methods/oidc.py
hvac/api/auth_methods/okta.py
hvac/api/auth_methods/radius.py
hvac/api/auth_methods/token.py
hvac/api/auth_methods/userpass.py
hvac/api/secrets_engines/__init__.py
hvac/api/secrets_engines/active_directory.py
hvac/api/secrets_engines/aws.py
hvac/api/secrets_engines/azure.py
hvac/api/secrets_engines/consul.py
hvac/api/secrets_engines/database.py
hvac/api/secrets_engines/gcp.py
hvac/api/secrets_engines/identity.py
hvac/api/secrets_engines/kv.py
hvac/api/secrets_engines/kv_v1.py
hvac/api/secrets_engines/kv_v2.py
hvac/api/secrets_engines/pki.py
hvac/api/secrets_engines/rabbitmq.py
hvac/api/secrets_engines/ssh.py
hvac/api/secrets_engines/transform.py
hvac/api/secrets_engines/transit.py
hvac/api/system_backend/__init__.py
hvac/api/system_backend/audit.py
hvac/api/system_backend/auth.py
hvac/api/system_backend/capabilities.py
hvac/api/system_backend/health.py
hvac/api/system_backend/init.py
hvac/api/system_backend/key.py
hvac/api/system_backend/leader.py
hvac/api/system_backend/lease.py
hvac/api/system_backend/mount.py
hvac/api/system_backend/namespace.py
hvac/api/system_backend/policy.py
hvac/api/system_backend/raft.py
hvac/api/system_backend/seal.py
hvac/api/system_backend/system_backend_mixin.py
hvac/api/system_backend/wrapping.py
hvac/api/vault_api_base.py
hvac/api/vault_api_category.py
hvac/aws_utils.py
hvac/constants/__init__.py
hvac/constants/approle.py
hvac/constants/aws.py
hvac/constants/azure.py
hvac/constants/client.py
hvac/constants/gcp.py
hvac/constants/identity.py
hvac/constants/transit.py
hvac-1.2.0.dist-info/LICENSE.txt
hvac-1.2.0.dist-info/METADATA
hvac-1.2.0.dist-info/WHEEL
hvac-1.2.0.dist-info/RECORD
