Metadata-Version: 2.1
Name: hvac
Version: 1.2.0
Summary: HashiCorp Vault API client
Home-page: https://github.com/hvac/hvac
License: Apache-2.0
Keywords: hashicorp,vault
Author: Ian Unruh
Author-email: ianunruh@gmail.com
Maintainer: Brian Scholer
Requires-Python: >=3.6.2,<4.0.0
Classifier: License :: OSI Approved :: Apache Software License
Classifier: Programming Language :: Python
Classifier: Programming Language :: Python :: 3
Classifier: Programming Language :: Python :: 3.7
Classifier: Programming Language :: Python :: 3.8
Classifier: Programming Language :: Python :: 3.9
Classifier: Programming Language :: Python :: 3.10
Classifier: Programming Language :: Python :: 3.11
Classifier: Programming Language :: Python :: 3
Classifier: Programming Language :: Python :: 3.10
Classifier: Programming Language :: Python :: 3.6
Classifier: Programming Language :: Python :: 3.7
Classifier: Programming Language :: Python :: 3.8
Classifier: Programming Language :: Python :: 3.9
Classifier: Programming Language :: Python :: Implementation :: CPython
Requires-Dist: pyhcl (>=0.4.4,<0.5.0)
Requires-Dist: requests (>=2.27.1,<3.0.0)
Project-URL: Documentation, https://hvac.readthedocs.io/en/stable/overview.html
Project-URL: Repository, https://github.com/hvac/hvac
